shinuk/__init__.py
shinuk/keypoints.py
shinuk/load_state.py
shinuk/model.py
shinuk/module.py
shinuk/pose.py
shinuk/proccessing.py
shinuk/util.py
shinuk/val.py
shinuk-1.1.3.dist-info/METADATA
shinuk-1.1.3.dist-info/WHEEL
shinuk-1.1.3.dist-info/top_level.txt
shinuk-1.1.3.dist-info/RECORD
