Metadata-Version: 2.1
Name: shinuk
Version: 1.1.3
Summary: Python wrapper for pose_estimation
Home-page: https://github.com/wook3024/pose_estimation_torchserve/shinuk
Author: Shinuk Yi
Author-email: wook3024@gmail.com
License: UNKNOWN
Download-URL: https://github.com/wook3024/pose_estimation_torchserve/shinuk
Keywords: pose_estimation,torchserve
Platform: UNKNOWN
Classifier: Programming Language :: Python :: 3
Classifier: Programming Language :: Python :: 3.2
Classifier: Programming Language :: Python :: 3.3
Classifier: Programming Language :: Python :: 3.4
Classifier: Programming Language :: Python :: 3.5
Classifier: Programming Language :: Python :: 3.6
Requires-Python: >=3
